latentmi/__init__.py
latentmi/ksg.py
latentmi/lmi.py
latentmi/models.py
latentmi-0.1.3.dist-info/LICENSE
latentmi-0.1.3.dist-info/METADATA
latentmi-0.1.3.dist-info/WHEEL
latentmi-0.1.3.dist-info/RECORD
